{
    "details": "Generated for necu20 at 2021-02-27 11:30:02.",
    "key": "1fd1eeb2f63a8550c663e9263dacc2e7",
    "summary": {
        "questions": 9,
        "points": 13,
        "pass": 8,
        "passdistinct": 13
    },
    "points": {
        "1.1": 1,
        "1.2": 1,
        "1.3": 1,
        "1.4": 1,
        "1.5": 1,
        "1.6": 1,
        "1.7": 1,
        "2.1": 3,
        "2.2": 3
    },
    "answers": {
        "1.1": {
            "Chandler": 55523645,
            "Monica": 55564452,
            "Ross": 55545872
        },
        "1.2": 3,
        "1.3": 55545872,
        "1.4": [
            "Chandler",
            "Monica",
            "Ross"
        ],
        "1.5": [
            55523645,
            55545872,
            55564452
        ],
        "1.6": true,
        "1.7": {
            "Chandler": 55523645,
            "Monica": 55564452
        },
        "2.1": "Chandler 55523645\nMonica 55564452\nRoss 55545872\n",
        "2.2": {
            "Chandler": "+1-55523645",
            "Monica": "+1-55564452",
            "Ross": "+1-55545872"
        }
    }
}